{
  "parent": "minecraft:recipes/root",
  "rewards": {
    "recipes": [
      "frt:destabilized_coal"
    ]
  },
  "criteria": {
    "has_the_ingredient": {
      "trigger": "minecraft:inventory_changed",
      "conditions": {
        "items": [
          {
            "item": "frt:charged_coal"
          }
        ]
      }
    },
    "has_the_recipe": {
      "trigger": "minecraft:recipe_unlocked",
      "conditions": {
        "recipe": "frt:destabilized_coal"
      }
    }
  },
  "requirements": [
    [
      "has_the_ingredient",
      "has_the_recipe"
    ]
  ]
}